uw_nws/VERSION
uw_nws/__init__.py
uw_nws/dao.py
uw_nws/exceptions.py
uw_nws/models.py
uw_nws/test.py
uw_nws/utilities.py
uw_nws/resources/nws/file/notification/v1/channel_expires_after_2013-05-31T00_00_00_tag_quarter_spring_tag_year_2013_type_uw_student_courseavailable
uw_nws/resources/nws/file/notification/v1/channel_surrogate_id_2012_autumn_cse_100_w_type_uw_student_courseavailable
uw_nws/resources/nws/file/notification/v1/channel_tag_quarter_autumn_tag_sln_12345_tag_year_2012_type_uw_student_courseavailable
uw_nws/resources/nws/file/notification/v1/channel_tag_quarter_autumn_tag_year_2013
uw_nws/resources/nws/file/notification/v1/channel_tag_quarter_spring_tag_sln_12345_tag_year_2013_type_uw_student_courseavailable
uw_nws/resources/nws/file/notification/v1/channel_tag_quarter_spring_tag_year_2013
uw_nws/resources/nws/file/notification/v1/channel_tag_quarter_summer_tag_year_2013
uw_nws/resources/nws/file/notification/v1/channel_tag_quarter_winter_tag_year_2014
uw_nws/resources/nws/file/notification/v1/channel_tag_sln_12345_type_uw_student_courseavailable
uw_nws/resources/nws/file/notification/v1/endpoint_endpoint_address_123-456-7890
uw_nws/resources/nws/file/notification/v1/endpoint_endpoint_address_222-222-3333
uw_nws/resources/nws/file/notification/v1/endpoint_subscriber_id_javerage
uw_nws/resources/nws/file/notification/v1/endpoint_subscriber_id_javerage_protocol_email
uw_nws/resources/nws/file/notification/v1/endpoint_subscriber_id_javerage_protocol_sms
uw_nws/resources/nws/file/notification/v1/endpoint_subscriber_id_javerage_washington.edu
uw_nws/resources/nws/file/notification/v1/subscription_channel_id_b779df7b-d6f6-4afb-8165-8dbe6232119f
uw_nws/resources/nws/file/notification/v1/subscription_channel_id_b779df7b-d6f6-4afb-8165-8dbe6232119f_endpoint_id_780f2a49-2118-4969-9bef-bbd38c26970a
uw_nws/resources/nws/file/notification/v1/subscription_channel_id_b779df7b-d6f6-4afb-8165-8dbe6232119f_person_id_9136CCB8F66711D5BE060004AC494FFE
UW_RestClients_NWS-1.3.5.dist-info/LICENSE
UW_RestClients_NWS-1.3.5.dist-info/METADATA
UW_RestClients_NWS-1.3.5.dist-info/WHEEL
UW_RestClients_NWS-1.3.5.dist-info/top_level.txt
UW_RestClients_NWS-1.3.5.dist-info/RECORD
