Metadata-Version: 2.1
Name: UW-RestClients-NWS
Version: 1.3.5
Summary: A library for connecting to the Notification Web Service at the University of Washington
Home-page: https://github.com/uw-it-aca/uw-restclients-nws
Author: UW-IT AXDD
Author-email: aca-it@uw.edu
License: Apache License, Version 2.0
Platform: UNKNOWN
Classifier: Intended Audience :: Developers
Classifier: License :: OSI Approved :: Apache Software License
Classifier: Operating System :: OS Independent
Classifier: Programming Language :: Python
Classifier: Programming Language :: Python :: 3.6
Requires-Dist: UW-RestClients-Core
Requires-Dist: python-dateutil
Requires-Dist: mock
